llm_structured_output_Detect_repairs/__init__.py
llm_structured_output_Detect_repairs/llm_output_parser.py
llm_structured_output_Detect_repairs-0.1.4.dist-info/LICENSE
llm_structured_output_Detect_repairs-0.1.4.dist-info/METADATA
llm_structured_output_Detect_repairs-0.1.4.dist-info/WHEEL
llm_structured_output_Detect_repairs-0.1.4.dist-info/top_level.txt
llm_structured_output_Detect_repairs-0.1.4.dist-info/RECORD
