Metadata-Version: 2.1
Name: llm_structured_output_Detect_repairs
Version: 0.1.4
Summary: 一个简单的HTTP客户端库，用于与结构化输出API交互
Author: jiayanfeng
Author-email: jyf_bit@163.com
Classifier: Programming Language :: Python :: 3
Classifier: License :: OSI Approved :: MIT License
Classifier: Operating System :: OS Independent
Requires-Python: >=3.6
License-File: LICENSE
Requires-Dist: requests
Requires-Dist: langchain
Requires-Dist: openai
